flask_rev.py
setup.cfg
setup.py
Flask_Rev.egg-info/PKG-INFO
Flask_Rev.egg-info/SOURCES.txt
Flask_Rev.egg-info/dependency_links.txt
Flask_Rev.egg-info/not-zip-safe
Flask_Rev.egg-info/requires.txt
Flask_Rev.egg-info/top_level.txt