Metadata-Version: 1.1
Name: Flask-Rev
Version: 0.1.2
Summary: Easily integrate flask with revisioned static files
Home-page: https://github.com/italomaia/flask-rev
Author: Italo Maia
Author-email: italo.maia@gmail.com
License: BSD
Platform: any
Classifier: Environment :: Web Environment
Classifier: Intended Audience :: Developers
Classifier: License :: OSI Approved :: BSD License
Classifier: Operating System :: OS Independent
Classifier: Programming Language :: Python
Classifier: Topic :: Internet :: WWW/HTTP :: Dynamic Content
Classifier: Topic :: Software Development :: Libraries :: Python Modules
